setup.py
hyMethod/Function.py
hyMethod/__init__.py
hyMethod.egg-info/PKG-INFO
hyMethod.egg-info/SOURCES.txt
hyMethod.egg-info/dependency_links.txt
hyMethod.egg-info/top_level.txt